csirtg_ipsml
test
