Metadata-Version: 1.0
Name: csirtg-ipsml
Version: 0.0.0a3
Summary: CSIRTG IP ML Framework
Home-page: https://github.com/csirtgadgets/csirtg-ipsml
Author: Wes Young
Author-email: wes@barely3am.com
License: MPL2
Keywords: network,security
Platform: UNKNOWN
